odoo/addons/analytic_base_department/README.rst
odoo/addons/analytic_base_department/__init__.py
odoo/addons/analytic_base_department/__manifest__.py
odoo/addons/analytic_base_department/i18n/analytic_base_department.pot
odoo/addons/analytic_base_department/i18n/ca.po
odoo/addons/analytic_base_department/i18n/de.po
odoo/addons/analytic_base_department/i18n/el_GR.po
odoo/addons/analytic_base_department/i18n/es.po
odoo/addons/analytic_base_department/i18n/es_CO.po
odoo/addons/analytic_base_department/i18n/es_MX.po
odoo/addons/analytic_base_department/i18n/fi.po
odoo/addons/analytic_base_department/i18n/fr.po
odoo/addons/analytic_base_department/i18n/gu_IN.po
odoo/addons/analytic_base_department/i18n/hi_IN.po
odoo/addons/analytic_base_department/i18n/hr_HR.po
odoo/addons/analytic_base_department/i18n/it.po
odoo/addons/analytic_base_department/i18n/nl.po
odoo/addons/analytic_base_department/i18n/pt.po
odoo/addons/analytic_base_department/i18n/pt_BR.po
odoo/addons/analytic_base_department/i18n/sk_SK.po
odoo/addons/analytic_base_department/i18n/sl.po
odoo/addons/analytic_base_department/i18n/zh_CN.po
odoo/addons/analytic_base_department/models/__init__.py
odoo/addons/analytic_base_department/models/analytic.py
odoo/addons/analytic_base_department/models/hr_department.py
odoo/addons/analytic_base_department/readme/CONTRIBUTORS.md
odoo/addons/analytic_base_department/readme/DESCRIPTION.md
odoo/addons/analytic_base_department/readme/HISTORY.md
odoo/addons/analytic_base_department/static/description/icon.png
odoo/addons/analytic_base_department/static/description/index.html
odoo/addons/analytic_base_department/tests/__init__.py
odoo/addons/analytic_base_department/tests/test_line_department.py
odoo/addons/analytic_base_department/views/analytic.xml
odoo/addons/analytic_base_department/views/hr_department_views.xml
odoo_addon_analytic_base_department-18.0.1.0.0.5.dist-info/METADATA
odoo_addon_analytic_base_department-18.0.1.0.0.5.dist-info/WHEEL
odoo_addon_analytic_base_department-18.0.1.0.0.5.dist-info/top_level.txt
odoo_addon_analytic_base_department-18.0.1.0.0.5.dist-info/RECORD
