Metadata-Version: 2.1
Name: odoo-addon-analytic_base_department
Version: 18.0.1.0.0.5
Requires-Python: >=3.10
Requires-Dist: odoo==18.0.*
Summary: Add relationship between Analytic and Department
Home-page: https://github.com/OCA/account-analytic
License: AGPL-3
Author: Camptocamp, Daniel Reis, Odoo Community Association (OCA)
Author-email: support@odoo-community.org
Classifier: Programming Language :: Python
Classifier: Framework :: Odoo
Classifier: Framework :: Odoo :: 18.0
Classifier: License :: OSI Approved :: GNU Affero General Public License v3
